kraken_sdk/__init__.py
kraken_sdk/api/__init__.py
kraken_sdk/api/admin_workspaces_api.py
kraken_sdk/api/api_keys_api.py
kraken_sdk/api/attacks_api.py
kraken_sdk/api/authentication_api.py
kraken_sdk/api/domains_api.py
kraken_sdk/api/global_tags_api.py
kraken_sdk/api/hosts_api.py
kraken_sdk/api/leech_management_api.py
kraken_sdk/api/o_auth_api.py
kraken_sdk/api/o_auth_application_api.py
kraken_sdk/api/o_auth_decisions_api.py
kraken_sdk/api/ports_api.py
kraken_sdk/api/services_api.py
kraken_sdk/api/settings_management_api.py
kraken_sdk/api/user_admin_management_api.py
kraken_sdk/api/user_management_api.py
kraken_sdk/api/websocket_api.py
kraken_sdk/api/wordlist_api.py
kraken_sdk/api/wordlist_management_api.py
kraken_sdk/api/workspace_invitations_api.py
kraken_sdk/api/workspace_tags_api.py
kraken_sdk/api/workspaces_api.py
kraken_sdk/api_client.py
kraken_sdk/api_response.py
kraken_sdk/configuration.py
kraken_sdk/exceptions.py
kraken_sdk/models/__init__.py
kraken_sdk/models/api_error_response.py
kraken_sdk/models/api_status_code.py
kraken_sdk/models/attack_type.py
kraken_sdk/models/bruteforce_subdomains_request.py
kraken_sdk/models/bruteforce_subdomains_results_page.py
kraken_sdk/models/certificate_transparency_entry.py
kraken_sdk/models/color.py
kraken_sdk/models/create_api_key_request.py
kraken_sdk/models/create_app_request.py
kraken_sdk/models/create_domain_request.py
kraken_sdk/models/create_global_tag_request.py
kraken_sdk/models/create_host_request.py
kraken_sdk/models/create_leech_request.py
kraken_sdk/models/create_port_request.py
kraken_sdk/models/create_service_request.py
kraken_sdk/models/create_user_request.py
kraken_sdk/models/create_wordlist_request.py
kraken_sdk/models/create_workspace_request.py
kraken_sdk/models/create_workspace_tag_request.py
kraken_sdk/models/dns_resolution_request.py
kraken_sdk/models/dns_resolution_results_page.py
kraken_sdk/models/domain_certainty.py
kraken_sdk/models/domain_results_page.py
kraken_sdk-0.1.0.dist-info/METADATA
kraken_sdk-0.1.0.dist-info/WHEEL
kraken_sdk-0.1.0.dist-info/RECORD
