Metadata-Version: 2.1
Name: kraken_sdk
Version: 0.1.0
Summary: kraken
Home-page: https://github.com/myOmikron/kraken-project
License: AGPL-3.0
Keywords: OpenAPI,OpenAPI-Generator,kraken
Author: Niklas Pfister
Author-email: git@omikron.dev
Requires-Python: >=3.7,<4.0
Classifier: License :: OSI Approved :: GNU Affero General Public License v3
Classifier: Programming Language :: Python :: 3
Classifier: Programming Language :: Python :: 3.7
Classifier: Programming Language :: Python :: 3.8
Classifier: Programming Language :: Python :: 3.9
Classifier: Programming Language :: Python :: 3.10
Classifier: Programming Language :: Python :: 3.11
Classifier: Programming Language :: Python :: 3.12
Requires-Dist: aiohttp (>=3.8.4)
Requires-Dist: pydantic (>=2)
Requires-Dist: python-dateutil (>=2.8.2)
Requires-Dist: typing-extensions (>=4.7.1)
Requires-Dist: urllib3 (>=1.25.3)
Project-URL: Repository, https://github.com/myOmikron/kraken-project
